rxflow/__init__.py
rxflow/elements.py
rxflow/utils.py
rxflow-0.0.2.dist-info/LICENSE
rxflow-0.0.2.dist-info/METADATA
rxflow-0.0.2.dist-info/WHEEL
rxflow-0.0.2.dist-info/top_level.txt
rxflow-0.0.2.dist-info/RECORD
