Metadata-Version: 2.1
Name: rxflow
Version: 0.0.2
Summary: Minimalistic library for reactive state management
Author: Abhishek Chadha
License: UNKNOWN
Platform: UNKNOWN
Classifier: Programming Language :: Python :: 3
Classifier: License :: OSI Approved :: MIT License
Classifier: Operating System :: OS Independent
Requires-Python: >=3.6
License-File: LICENSE
